micromapper/Micromapper.py
micromapper/__init__.py
mapperscript-0.0.1.dist-info/LICENSE
mapperscript-0.0.1.dist-info/METADATA
mapperscript-0.0.1.dist-info/WHEEL
mapperscript-0.0.1.dist-info/top_level.txt
mapperscript-0.0.1.dist-info/RECORD
