Metadata-Version: 2.1
Name: mapperscript
Version: 0.0.1
Summary: Dynamic
Home-page: https://github.com/xxninjabunnyxx/micromapper
Author: xxninjabunnyxx
Author-email: xxninjabunnyxx@gmail.com
Project-URL: Bug Tracker, https://github.com/xxninjabunnyxx/micromapper/issues
Classifier: Programming Language :: Python :: 3
Classifier: License :: OSI Approved :: MIT License
Classifier: Operating System :: OS Independent
Requires-Python: >=3.6
License-File: LICENSE
